agrodigital_io/__init__.py
agrodigital_io-0.1.2.dist-info/METADATA
agrodigital_io-0.1.2.dist-info/WHEEL
agrodigital_io-0.1.2.dist-info/licenses/LICENSE
agrodigital_io-0.1.2.dist-info/RECORD
