Metadata-Version: 2.4
Name: agrodigital_io
Version: 0.1.2
Summary: Python SDK for agrodigital.io.
License-File: LICENSE
Author: Joaquin Peraza
Author-email: joaquin@peraza.uy
Requires-Python: >=3.10
Classifier: Programming Language :: Python :: 3
Classifier: Programming Language :: Python :: 3.10
Classifier: Programming Language :: Python :: 3.11
Classifier: Programming Language :: Python :: 3.12
Classifier: Programming Language :: Python :: 3.13
Classifier: Programming Language :: Python :: 3.14
Requires-Dist: requests (>=2.32.5,<3.0.0)
